sonorus/__init__.py
sonorus/audio/AudioInputStreamer.py
sonorus/audio/VADAudioInputStreamer.py
sonorus/audio/__init__.py
sonorus/audio/praat.py
sonorus/audio/utils.py
sonorus/experimental/__init__.py
sonorus/experimental/datasets/CommonVoice.py
sonorus/experimental/datasets/__init__.py
sonorus/experimental/datasets/utils.py
sonorus/experimental/modules/DataCollatorWav2Vec2.py
sonorus/experimental/modules/__init__.py
sonorus/experimental/modules/utils.py
sonorus/speech/GoogleSTT.py
sonorus/speech/Wav2Vec2STT.py
sonorus/speech/__init__.py
sonorus/speech/utils.py
sonorus/speech/kaldi/PhonemeSegmenter.py
sonorus/speech/kaldi/__init__.py
sonorus/speech/kaldi/create_confs.py
sonorus/speech/kaldi/utils.py
sonorus/speech/kaldi/conf/ivector_extractor.conf
sonorus/speech/kaldi/conf/mfcc.conf
sonorus/speech/kaldi/conf/online_cmvn.conf
sonorus/speech/kaldi/conf/splice.conf
sonorus/speech/lm/FairseqLM.py
sonorus/speech/lm/FairseqTokenDictionary.py
sonorus/speech/lm/W2lDecoder.py
sonorus/speech/lm/W2lFairseqLMDecoder.py
sonorus/speech/lm/W2lKenLMDecoder.py
sonorus/speech/lm/W2lViterbiDecoder.py
sonorus/speech/lm/__init__.py
sonorus/speech/lm/generate.py
sonorus/utilities/__init__.py
sonorus/utilities/utils.py
sonorus/utilities/multi_proc_thread/MultiProcessor.py
sonorus/utilities/multi_proc_thread/MultiProducerSingleConsumer.py
sonorus/utilities/multi_proc_thread/Processor.py
sonorus/utilities/multi_proc_thread/SingleProcessor.py
sonorus/utilities/multi_proc_thread/__init__.py
sonorus-0.1.1.dist-info/LICENSE.md
sonorus-0.1.1.dist-info/METADATA
sonorus-0.1.1.dist-info/WHEEL
sonorus-0.1.1.dist-info/top_level.txt
sonorus-0.1.1.dist-info/RECORD
