Metadata-Version: 2.1
Name: sonorus
Version: 0.1.1
Summary: Named after a spell in the Harry Potter Universe, where it      amplies the sound of a speaker. In muggles' terminology, this is a repository      of modules for audio and speech processing for and on top of machine learning      based tasks such as speech-to-text.
Home-page: https://github.com/pensieves/sonorus
Author: Md Imbesat Hassan Rizvi
Author-email: imbugene@gmail.com
License: MIT
Download-URL: https://github.com/pensieves/sonorus/releases
Keywords: deep learning,speech recognition,speech to text,language modelling
Platform: UNKNOWN
Classifier: Programming Language :: Python :: 3
Classifier: Development Status :: 3 - Alpha
Classifier: Intended Audience :: Developers
Classifier: License :: OSI Approved :: MIT License
Classifier: Environment :: GPU :: NVIDIA CUDA :: 11.2
Requires-Dist: six (~=1.15.0)
Requires-Dist: numpy (~=1.20.2)
Requires-Dist: scipy (~=1.6.2)
Requires-Dist: webrtcvad (~=2.0.10)
Requires-Dist: pyaudio (~=0.2.11)
Requires-Dist: librosa (~=0.8.0)
Requires-Dist: tqdm (~=4.49.0)
Requires-Dist: torch (~=1.7.1)
Requires-Dist: transformers (~=4.4.2)
Requires-Dist: omegaconf (~=2.0.6)
Requires-Dist: google-cloud-speech (~=2.0.1)
Requires-Dist: pandas (~=1.2.4)
Requires-Dist: datasets (~=1.5.0)
Requires-Dist: praat-parselmouth (~=0.4.0)
Requires-Dist: wget (~=3.2)
Provides-Extra: kaldi
Requires-Dist: pykaldi (~=0.2.1) ; extra == 'kaldi'
Provides-Extra: speechlm
Requires-Dist: pyflashlight ; extra == 'speechlm'
Requires-Dist: fairseq (~=1.0.0) ; extra == 'speechlm'
Requires-Dist: kenlm ; extra == 'speechlm'
